fli/__init__.py
fli/cli/__init__.py
fli/cli/console.py
fli/cli/enums.py
fli/cli/main.py
fli/cli/utils.py
fli/cli/commands/__init__.py
fli/cli/commands/dates.py
fli/cli/commands/flights.py
fli/core/__init__.py
fli/core/builders.py
fli/core/parsers.py
fli/mcp/__init__.py
fli/mcp/server.py
fli/models/__init__.py
fli/models/airline.py
fli/models/airport.py
fli/models/google_flights/__init__.py
fli/models/google_flights/base.py
fli/models/google_flights/dates.py
fli/models/google_flights/flights.py
fli/search/__init__.py
fli/search/client.py
fli/search/dates.py
fli/search/flights.py
flights-0.7.0.dist-info/METADATA
flights-0.7.0.dist-info/WHEEL
flights-0.7.0.dist-info/entry_points.txt
flights-0.7.0.dist-info/licenses/LICENSE.txt
flights-0.7.0.dist-info/RECORD
