Metadata-Version: 2.4
Name: flights
Version: 0.7.0
Summary: A Python wrapper for Google Flights API
Project-URL: Homepage, https://github.com/punitarani/fli
Project-URL: Repository, https://github.com/punitarani/fli
Project-URL: Documentation, https://punitarani.github.io/fli
Author-email: Punit Arani <punit@joinslash.com>
License: MIT
License-File: LICENSE.txt
Keywords: api,flight-search,flights,google-flights,travel
Classifier: Development Status :: 4 - Beta
Classifier: Intended Audience :: Developers
Classifier: License :: OSI Approved :: MIT License
Classifier: Programming Language :: Python :: 3
Classifier: Programming Language :: Python :: 3.10
Classifier: Programming Language :: Python :: 3.11
Classifier: Programming Language :: Python :: 3.12
Classifier: Programming Language :: Python :: 3.13
Classifier: Topic :: Internet :: WWW/HTTP :: Indexing/Search
Classifier: Topic :: Software Development :: Libraries :: Python Modules
Requires-Python: >=3.10
Requires-Dist: curl-cffi>=0.7.4
Requires-Dist: fastapi>=0.115.6
Requires-Dist: fastmcp>=0.1.0
Requires-Dist: httpx>=0.28.1
Requires-Dist: pandas>=2.2.3
Requires-Dist: plotext>=5.3.2
Requires-Dist: pydantic>=2.10.4
Requires-Dist: python-dotenv>=1.0.1
Requires-Dist: ratelimit>=2.2.1
Requires-Dist: tenacity>=9.0.0
Requires-Dist: typer>=0.15.1
Requires-Dist: uvicorn>=0.34.0
Provides-Extra: dev
Requires-Dist: mkdocs-material[imaging]>=9.5.49; extra == 'dev'
Requires-Dist: mkdocstrings[python]>=0.27.0; extra == 'dev'
Requires-Dist: pytest-asyncio>=0.25.2; extra == 'dev'
Requires-Dist: pytest-cov>=6.0.0; extra == 'dev'
Requires-Dist: pytest-xdist>=3.6.1; extra == 'dev'
Requires-Dist: pytest>=8.3.4; extra == 'dev'
Requires-Dist: ruff>=0.8.4; extra == 'dev'
Requires-Dist: twine>=6.0.0; extra == 'dev'
